django_cloudevents/__init__.py
django_cloudevents/_compat.py
django_cloudevents/apps.py
django_cloudevents/conf.py
django_cloudevents/processors.py
django_cloudevents/py.typed
django_cloudevents/signals.py
django_cloudevents/urls.py
django_cloudevents/views.py
django_cloudevents-0.0.1.dist-info/METADATA
django_cloudevents-0.0.1.dist-info/WHEEL
django_cloudevents-0.0.1.dist-info/licenses/LICENSE.txt
django_cloudevents-0.0.1.dist-info/RECORD
