Metadata-Version: 2.3
Name: django-cloudevents
Version: 0.0.1
Summary: Simple health checking for django applications
Project-URL: Documentation, https://github.com/hartungstenio/django-cloudevents#readme
Project-URL: Issues, https://github.com/hartungstenio/django-cloudevents/issues
Project-URL: Source, https://github.com/hartungstenio/django-cloudevents
Author-email: Christian Hartung <hartung@live.com>
License: MIT
Keywords: django
Classifier: Development Status :: 4 - Beta
Classifier: Framework :: Django :: 4.2
Classifier: Framework :: Django :: 5.0
Classifier: Framework :: Django :: 5.1
Classifier: Programming Language :: Python
Classifier: Programming Language :: Python :: 3.9
Classifier: Programming Language :: Python :: 3.10
Classifier: Programming Language :: Python :: 3.11
Classifier: Programming Language :: Python :: 3.12
Classifier: Programming Language :: Python :: 3.13
Classifier: Programming Language :: Python :: Implementation :: CPython
Classifier: Programming Language :: Python :: Implementation :: PyPy
Requires-Python: >=3.9
Requires-Dist: asgiref>=3.3
Requires-Dist: cloudevents
Requires-Dist: django>=4.2
Requires-Dist: typing-extensions; python_version < '3.12'
